hpyx/__init__.py
hpyx/_core.cpython-313t-darwin.so
hpyx/_version.py
hpyx/executor.py
hpyx/futures/__init__.py
hpyx/futures/_submit.py
hpyx/multiprocessing/__init__.py
hpyx/multiprocessing/_for_loop.py
hpyx/runtime.py
hpyx/util/__init__.py
hpyx/util/print_versions.py
hpyx-2025.8.28.dist-info/METADATA
hpyx-2025.8.28.dist-info/WHEEL
hpyx-2025.8.28.dist-info/licenses/LICENSE
hpyx-2025.8.28.dist-info/RECORD
