Metadata-Version: 2.1
Name: hpyx
Version: 2025.8.28
Summary: Python Binding for HPX C++ library
License: BSD 3-Clause License
Classifier: Development Status :: 3 - Alpha
Classifier: Intended Audience :: Developers
Classifier: License :: OSI Approved :: BSD License
Classifier: Operating System :: OS Independent
Classifier: Programming Language :: Python :: 3.13
Classifier: Topic :: Scientific/Engineering
Classifier: Topic :: Software Development :: Build Tools
Classifier: Topic :: Software Development :: Libraries :: Python Modules
Project-URL: Homepage, https://github.com/uw-ssec/HPyX
Project-URL: Documentation, https://ssec-hypx.readthedocs.io
Project-URL: Repository, https://github.com/uw-ssec/hpyx.git
Project-URL: Issues, https://github.com/uw-ssec/HPyX/issues
Requires-Python: >=3.13
Requires-Dist: numpy
Provides-Extra: dev
Requires-Dist: pre-commit; extra == "dev"
Requires-Dist: pytest>=8; extra == "dev"
Requires-Dist: pytest-cov; extra == "dev"
Requires-Dist: pytest-xdist; extra == "dev"
Requires-Dist: pytest-mock; extra == "dev"
Provides-Extra: docs
Requires-Dist: sphinx_rtd_theme; extra == "docs"
Requires-Dist: sphinx-automodapi; extra == "docs"
Requires-Dist: sphinx-panels; extra == "docs"
Requires-Dist: sphinxcontrib-mermaid; extra == "docs"
Requires-Dist: jupyter-book; extra == "docs"
Requires-Dist: numpydoc; extra == "docs"
Provides-Extra: all
Requires-Dist: hpyx[dev,docs]; extra == "all"
